libname/__init__.py
libname/hello.py
hello_lib-0.0.1.dist-info/METADATA
hello_lib-0.0.1.dist-info/WHEEL
hello_lib-0.0.1.dist-info/top_level.txt
hello_lib-0.0.1.dist-info/RECORD
